thongtinthuoc/__init__.py
thongtinthuoc-0.2.0.dist-info/METADATA
thongtinthuoc-0.2.0.dist-info/WHEEL
thongtinthuoc-0.2.0.dist-info/top_level.txt
thongtinthuoc-0.2.0.dist-info/RECORD
